cloudfiles/__init__.py
cloudfiles/cloudfiles.py
cloudfiles/compression.py
cloudfiles/connectionpools.py
cloudfiles/exceptions.py
cloudfiles/gcs.py
cloudfiles/interfaces.py
cloudfiles/lib.py
cloudfiles/monitoring.py
cloudfiles/paths.py
cloudfiles/resumable_tools.py
cloudfiles/scheduler.py
cloudfiles/secrets.py
cloudfiles/test.py
cloudfiles/threaded_queue.py
cloudfiles/typing.py
cloudfiles_cli/LICENSE
cloudfiles_cli/__init__.py
cloudfiles_cli/cloudfiles_cli.py
cloud_files-5.8.2.dist-info/AUTHORS
cloud_files-5.8.2.dist-info/LICENSE
cloud_files-5.8.2.dist-info/METADATA
cloud_files-5.8.2.dist-info/WHEEL
cloud_files-5.8.2.dist-info/entry_points.txt
cloud_files-5.8.2.dist-info/pbr.json
cloud_files-5.8.2.dist-info/top_level.txt
cloud_files-5.8.2.dist-info/RECORD
