Metadata-Version: 2.1
Name: cloud-files
Version: 5.8.2
Summary: Fast access to cloud storage and local FS.
Home-page: https://github.com/seung-lab/cloud-files/
Author: William Silversmith
Author-email: ws9@princeton.edu
License: BSD-3-Clause
Classifier: Intended Audience :: Developers
Classifier: Development Status :: 4 - Beta
Classifier: Programming Language :: Python :: 3
Classifier: Programming Language :: Python :: 3.9
Classifier: Programming Language :: Python :: 3.10
Classifier: Programming Language :: Python :: 3.11
Classifier: Programming Language :: Python :: 3.12
Classifier: Programming Language :: Python :: 3.13
Classifier: Topic :: Software Development :: Libraries :: Python Modules
Requires-Python: >=3.9,<4.0
License-File: LICENSE
License-File: AUTHORS
Requires-Dist: boto3 >=1.4.7
Requires-Dist: brotli
Requires-Dist: crc32c
Requires-Dist: chardet >=3.0.4
Requires-Dist: click
Requires-Dist: deflate >=0.2.0
Requires-Dist: gevent
Requires-Dist: google-auth >=1.10.0
Requires-Dist: google-cloud-core >=1.1.0
Requires-Dist: google-cloud-storage >=1.31.1
Requires-Dist: google-crc32c >=1.0.0
Requires-Dist: intervaltree
Requires-Dist: numpy
Requires-Dist: orjson
Requires-Dist: pathos
Requires-Dist: protobuf >=3.3.0
Requires-Dist: requests >=2.22.0
Requires-Dist: six >=1.14.0
Requires-Dist: tenacity >=4.10.0
Requires-Dist: tqdm
Requires-Dist: urllib3 >=1.26.3
Requires-Dist: zstandard
Requires-Dist: rsa >=4.7.2
Requires-Dist: fasteners
Provides-Extra: apache
Requires-Dist: lxml ; extra == 'apache'
Provides-Extra: monitoring
Requires-Dist: psutil ; extra == 'monitoring'
Requires-Dist: intervaltree ; extra == 'monitoring'
Requires-Dist: matplotlib ; extra == 'monitoring'
Provides-Extra: numpy
Requires-Dist: numpy ; extra == 'numpy'
Provides-Extra: test
Requires-Dist: pytest ; extra == 'test'
Requires-Dist: moto >=5 ; extra == 'test'
